arxiv_decent_feeds-0.0.2.dist-info/DESCRIPTION.rst
arxiv_decent_feeds-0.0.2.dist-info/METADATA
arxiv_decent_feeds-0.0.2.dist-info/RECORD
arxiv_decent_feeds-0.0.2.dist-info/WHEEL
arxiv_decent_feeds-0.0.2.dist-info/entry_points.txt
arxiv_decent_feeds-0.0.2.dist-info/metadata.json
arxiv_decent_feeds-0.0.2.dist-info/top_level.txt
arxivdf/__init__.py
arxivdf/adf.py
arxivdf/arxivdf.py
arxivdf/arxivreader.py
arxivdf/database.py
arxivdf/feedwriter.py
arxivdf/model.py
