Metadata-Version: 2.0
Name: arxiv-decent-feeds
Version: 0.0.2
Summary: Feed converer for arxiv feeds
Home-page: https://github.com/trovao/arxiv-decent-feeds
Author: Renato Cunha
Author-email: erangb@erangbphaun.pbz
License: MIT
Keywords: arxiv feed aggregator
Platform: UNKNOWN
Classifier: Development Status :: 3 - Alpha
Classifier: Programming Language :: Python :: 2
Requires-Dist: feedgen
Requires-Dist: feedparser
Requires-Dist: lxml
Requires-Dist: python-dateutil
Requires-Dist: pytz
Requires-Dist: requests
Requires-Dist: sqlalchemy
